cookiecutter.json
hooks/aioproc.py
hooks/post_gen_project.py
hooks/pre_gen_project.py
ppw/cli.py
{{cookiecutter.project_slug}}/.coveragerc
{{cookiecutter.project_slug}}/.docstring.tpl
{{cookiecutter.project_slug}}/.editorconfig
{{cookiecutter.project_slug}}/.flake8
{{cookiecutter.project_slug}}/.github/ISSUE_TEMPLATE.md
{{cookiecutter.project_slug}}/.github/workflows/dev.yml
{{cookiecutter.project_slug}}/.github/workflows/release.yml
{{cookiecutter.project_slug}}/.gitignore
{{cookiecutter.project_slug}}/.isort.cfg
{{cookiecutter.project_slug}}/.pre-commit-config.yaml
{{cookiecutter.project_slug}}/AUTHORS.md
{{cookiecutter.project_slug}}/CONTRIBUTING.md
{{cookiecutter.project_slug}}/HISTORY.md
{{cookiecutter.project_slug}}/LICENSE
{{cookiecutter.project_slug}}/README.md
{{cookiecutter.project_slug}}/docs/api.md
{{cookiecutter.project_slug}}/docs/authors.md
{{cookiecutter.project_slug}}/docs/contributing.md
{{cookiecutter.project_slug}}/docs/history.md
{{cookiecutter.project_slug}}/docs/index.md
{{cookiecutter.project_slug}}/docs/installation.md
{{cookiecutter.project_slug}}/docs/usage.md
{{cookiecutter.project_slug}}/mkdocs.yml
{{cookiecutter.project_slug}}/mypy.ini
{{cookiecutter.project_slug}}/pyproject.toml
{{cookiecutter.project_slug}}/pyrightconfig.json
{{cookiecutter.project_slug}}/repo.sh
{{cookiecutter.project_slug}}/tests/__init__.py
{{cookiecutter.project_slug}}/tests/test_app.py
{{cookiecutter.project_slug}}/tox.ini
{{cookiecutter.project_slug}}/{{cookiecutter.project_slug}}/__init__.py
{{cookiecutter.project_slug}}/{{cookiecutter.project_slug}}/app.py
{{cookiecutter.project_slug}}/{{cookiecutter.project_slug}}/cli.py
{{cookiecutter.project_slug}}/{{cookiecutter.project_slug}}/py.typed
ppw-1.3.5.dist-info/LICENSE
ppw-1.3.5.dist-info/METADATA
ppw-1.3.5.dist-info/WHEEL
ppw-1.3.5.dist-info/entry_points.txt
ppw-1.3.5.dist-info/RECORD
