Metadata-Version: 2.1
Name: ppw
Version: 1.3.5
Summary: A Wizard to create a skeleton python project with up-to-date technology
Home-page: https://github.com/zillionare/python-project-wizard
License: BSD-3-Clause
Keywords: cookiecutter,template,package
Author: Aaron Yang
Author-email: aaron_yang@jieyu.ai
Requires-Python: >=3.8,<4.0
Classifier: License :: OSI Approved :: BSD License
Classifier: Programming Language :: Python :: 3
Classifier: Programming Language :: Python :: 3.8
Classifier: Programming Language :: Python :: 3.9
Classifier: Programming Language :: Python :: 3.10
Classifier: Programming Language :: Python :: 3.11
Provides-Extra: dev
Requires-Dist: colorama (>=0.4.5,<0.5.0)
Requires-Dist: cookiecutter (==1.7.2)
Requires-Dist: fire (>=0.4.0,<0.5.0) ; extra == "dev"
Requires-Dist: livereload (>=2.6.3,<3.0.0) ; extra == "dev"
Requires-Dist: mike (>=1.1.2,<2.0.0) ; extra == "dev"
Requires-Dist: mkdocs (>=1.1.2,<2.0.0) ; extra == "dev"
Requires-Dist: mkdocs-include-markdown-plugin (>=2.8.0,<3.0.0) ; extra == "dev"
Requires-Dist: mkdocs-material (>=6.1.7,<7.0.0) ; extra == "dev"
Requires-Dist: mkdocs-material-extensions (>=1.0.1,<2.0.0) ; extra == "dev"
Requires-Dist: mypy (>=1.5.1,<2.0.0) ; extra == "dev"
Requires-Dist: pre-commit (>=2.18.1,<3.0.0)
Requires-Dist: pytest (>=6.2.5,<7.0.0) ; extra == "dev"
Requires-Dist: pytest-cookies (>=0.6.1,<0.7.0) ; extra == "dev"
Requires-Dist: pytest-cov (>=2.10.1,<3.0.0) ; extra == "dev"
Requires-Dist: pyyaml (>=6.0,<7.0) ; extra == "dev"
Requires-Dist: tox (>=3.20.1,<4.0.0) ; extra == "dev"
Project-URL: Documentation, https://zillionare.github.io/python-project-wizard/
Project-URL: Repository, https://github.com/zillionare/python-project-wizard
